arabela/__init__.py
arabela/cost_explorer/__init__.py
arabela/cost_explorer/get_cost_and_usage.py
test/__init__.py
test/cost_explorer/__init__.py
test/cost_explorer/test_get_cost_and_usage.py
arabela-0.0.4.dist-info/LICENSE
arabela-0.0.4.dist-info/METADATA
arabela-0.0.4.dist-info/WHEEL
arabela-0.0.4.dist-info/top_level.txt
arabela-0.0.4.dist-info/RECORD
