Metadata-Version: 2.1
Name: arabela
Version: 0.0.4
Summary: AWS SDK Declarative
Home-page: https://github.com/VunkLai/arabela
Author: Vunk.Lai
Author-email: vunk.lai@gmail.com
License: MIT
Platform: UNKNOWN
Classifier: Programming Language :: Python :: 3
Classifier: License :: OSI Approved :: MIT License
Classifier: Operating System :: OS Independent
Requires-Python: >=3.7
Requires-Dist: attrs (>=20.3.0)
